riyadhai/__init__.py
riyadhai/agents/__init__.py
riyadhai/agents/_exceptions.py
riyadhai/agents/inference_runner.py
riyadhai/agents/job.py
riyadhai/agents/jupyter.py
riyadhai/agents/log.py
riyadhai/agents/plugin.py
riyadhai/agents/py.typed
riyadhai/agents/types.py
riyadhai/agents/vad.py
riyadhai/agents/version.py
riyadhai/agents/worker.py
riyadhai/agents/beta/__init__.py
riyadhai/agents/beta/tools/send_dtmf.py
riyadhai/agents/beta/workflows/__init__.py
riyadhai/agents/beta/workflows/address.py
riyadhai/agents/beta/workflows/dtmf_inputs.py
riyadhai/agents/beta/workflows/email_address.py
riyadhai/agents/beta/workflows/task_group.py
riyadhai/agents/beta/workflows/utils.py
riyadhai/agents/beta/workflows/warm_transfer.py
riyadhai/agents/cli/__init__.py
riyadhai/agents/cli/cli.py
riyadhai/agents/cli/discover.py
riyadhai/agents/cli/log.py
riyadhai/agents/cli/proto.py
riyadhai/agents/cli/readchar.py
riyadhai/agents/cli/watcher.py
riyadhai/agents/inference/__init__.py
riyadhai/agents/inference/_utils.py
riyadhai/agents/inference/llm.py
riyadhai/agents/inference/stt.py
riyadhai/agents/inference/tts.py
riyadhai/agents/ipc/__init__.py
riyadhai/agents/ipc/channel.py
riyadhai/agents/ipc/inference_executor.py
riyadhai/agents/ipc/inference_proc_executor.py
riyadhai/agents/ipc/inference_proc_lazy_main.py
riyadhai/agents/ipc/job_executor.py
riyadhai/agents/ipc/job_proc_executor.py
riyadhai/agents/ipc/job_proc_lazy_main.py
riyadhai/agents/ipc/job_thread_executor.py
riyadhai/agents/ipc/log_queue.py
riyadhai/agents/ipc/mock_room.py
riyadhai/agents/ipc/proc_client.py
riyadhai/agents/ipc/proc_pool.py
riyadhai/agents/ipc/proto.py
riyadhai/agents/ipc/supervised_proc.py
riyadhai/agents/llm/__init__.py
riyadhai/agents/llm/_strict.py
riyadhai/agents/llm/chat_context.py
riyadhai/agents/llm/fallback_adapter.py
riyadhai/agents/llm/llm.py
riyadhai/agents/llm/mcp.py
riyadhai/agents/llm/realtime.py
riyadhai/agents/llm/remote_chat_context.py
riyadhai/agents/llm/tool_context.py
riyadhai-1.3.16.dist-info/licenses/LICENSE
riyadhai-1.3.16.dist-info/licenses/NOTICE
riyadhai-1.3.16.dist-info/METADATA
riyadhai-1.3.16.dist-info/WHEEL
riyadhai-1.3.16.dist-info/top_level.txt
riyadhai-1.3.16.dist-info/RECORD
