Metadata-Version: 2.4
Name: riyadhai
Version: 1.3.16
Summary: RiyadhAI Realtime Agents SDK
License:                                  Apache License
Keywords: ai,agents,audio,realtime,video,webrtc
Requires-Python: <3.14,>=3.10
License-File: LICENSE
License-File: NOTICE
Requires-Dist: aiofiles>=24
Requires-Dist: aiohttp~=3.10
Requires-Dist: av>=14.0.0
Requires-Dist: certifi>=2025.6.15
Requires-Dist: click~=8.1
Requires-Dist: colorama>=0.4.6
Requires-Dist: docstring-parser>=0.16
Requires-Dist: eval-type-backport
Requires-Dist: google-auth<3,>=2
Requires-Dist: google-cloud-speech<3,>=2
Requires-Dist: google-cloud-texttospeech<3,>=2.32
Requires-Dist: google-genai>=1.55; python_version >= "3.10"
Requires-Dist: jinja2
Requires-Dist: nest-asyncio>=1.6.0
Requires-Dist: numpy>=1.26.0
Requires-Dist: onnxruntime<=1.23.1,>=1.18
Requires-Dist: openai>=1.99.2
Requires-Dist: opentelemetry-api~=1.39.0
Requires-Dist: opentelemetry-exporter-otlp~=1.39.0
Requires-Dist: opentelemetry-sdk~=1.39.0
Requires-Dist: prometheus-client>=0.22
Requires-Dist: protobuf>=4.25.0
Requires-Dist: psutil>=7.0
Requires-Dist: pydantic<3,>=2.0
Requires-Dist: pyjwt>=2.0
Requires-Dist: sounddevice>=0.5
Requires-Dist: transformers<=4.57.1,>=4.47.1
Requires-Dist: typer>=0.15.1
Requires-Dist: types-protobuf>=4
Requires-Dist: typing-extensions>=4.12
Requires-Dist: watchfiles>=1.0
Provides-Extra: full
Requires-Dist: riyadhai-blingfire>=1.0.0; extra == "full"
Provides-Extra: mcp
Requires-Dist: mcp; extra == "mcp"
Dynamic: license-file
